odoo/addons/ssi_risk_analysis_related_attachment/README.rst
odoo/addons/ssi_risk_analysis_related_attachment/__init__.py
odoo/addons/ssi_risk_analysis_related_attachment/__manifest__.py
odoo/addons/ssi_risk_analysis_related_attachment/models/__init__.py
odoo/addons/ssi_risk_analysis_related_attachment/models/risk_analysis.py
odoo/addons/ssi_risk_analysis_related_attachment/static/description/icon.png
odoo14_addon_ssi_risk_analysis_related_attachment-14.0.1.0.1.dev2.dist-info/METADATA
odoo14_addon_ssi_risk_analysis_related_attachment-14.0.1.0.1.dev2.dist-info/WHEEL
odoo14_addon_ssi_risk_analysis_related_attachment-14.0.1.0.1.dev2.dist-info/top_level.txt
odoo14_addon_ssi_risk_analysis_related_attachment-14.0.1.0.1.dev2.dist-info/RECORD
